[
  {
    "question": "精子形成について正しいのはどれか。",
    "choices": {
      "a": "Leydig細胞は精細管内に存在する。",
      "b": "Leydig細胞はテストステロンを分泌する。",
      "c": "精液検査は採取後3時間経過してから行う。",
      "d": "精祖細胞から精子への形成には約28日を要する。",
      "e": "精子細胞から精子への分化は精巣上体内で起こる。"
    },
    "answer": "b",
    "explanation": "Leydig細胞は精巣の間質に存在し、テストステロンを分泌します。他の選択肢は誤りです。"
  },
  {
    "question": "両側水腎症の原因として誤っているのはどれか。",
    "choices": {
      "a": "馬蹄腎",
      "b": "二分脊椎",
      "c": "進行性胃癌",
      "d": "後部尿道弁",
      "e": "下大静脈後尿管"
    },
    "answer": "c",
    "explanation": "進行性胃癌は通常、両側の水腎症の原因とはなりません。他の選択肢は両側水腎症の原因となり得ます。"
  },
  {
    "question": "排尿痛がみられないのはどれか。",
    "choices": {
      "a": "膀胱異物",
      "b": "膀胱結石",
      "c": "急性前立腺炎",
      "d": "淋菌性尿道炎",
      "e": "尿道下裂"
    },
    "answer": "e",
    "explanation": "尿道下裂は先天的な尿道の開口異常であり、通常、排尿痛は伴いません。他の選択肢は排尿痛を引き起こす可能性があります。"
  },
  {
    "question": "褐色細胞腫について正しいのはどれか。",
    "choices": {
      "a": "局在診断に副腎静脈サンプリングが有用である。",
      "b": "123I-MIBGシンチグラフィが診断に用いられる。",
      "c": "β受容体遮断薬が第一選択で用いられる。",
      "d": "病理診断で悪性の有無を診断する。",
      "e": "腹腔鏡手術は適応とならない。"
    },
    "answer": "b",
    "explanation": "褐色細胞腫の診断には123I-MIBGシンチグラフィが有用です。他の選択肢は誤りです。"
  },
  {
    "question": "膀胱尿管逆流について正しいのはどれか。",
    "choices": {
      "a": "手術治療が第一選択である。",
      "b": "逆行性腎盂尿管造影によって診断する。",
      "c": "レノグラムで尿路の通過性を評価する。",
      "d": "有熱性尿路感染で発見されることが多い。",
      "e": "小児期に発見された場合、成長とともに悪化する。"
    },
    "answer": "d",
    "explanation": "膀胱尿管逆流は小児の有熱性尿路感染症で発見されることが多いです。他の選択肢は誤りです。"
  },
  {
    "question": "尿路結石について正しいのはどれか。",
    "choices": {
      "a": "シスチン結石はCTで同定困難である。",
      "b": "確定診断には静脈性尿路造影検査が行われる。",
      "c": "尿酸結石では尿酸排泄促進剤が予防に有用である。",
      "d": "疼痛緩和に非ステロイド性抗炎症薬が使用される。",
      "e": "発生する部位によって腎結石・尿管結石・膀胱結石と呼ばれる。"
    },
    "answer": "d",
    "explanation": "尿路結石の痛みの緩和には非ステロイド性抗炎症薬（NSAIDs）が有効です。他の選択肢は誤りです。"
  },
  {
    "question": "膀胱癌について正しいのはどれか。",
    "choices": {
      "a": "女性に多い。",
      "b": "腺癌が多い。",
      "c": "非乳頭状腫瘍が多い。",
      "d": "尿細胞診が有用である。",
      "e": "転移がなければ膀胱全摘除術の適応となる。"
    },
    "answer": "d",
    "explanation": "膀胱癌の診断には尿細胞診が有用です。他の選択肢は誤りです。"
  },
  {
    "question": "前立腺癌について誤っているのはどれか。",
    "choices": {
      "a": "血尿で発見されることが多い。",
      "b": "腺癌が多い。",
      "c": "前立腺針生検で診断する。",
      "d": "Gleasonスコアが病理診断の際に用いられる。",
      "e": "PSAがマーカーとなる。"
    },
    "answer": "a",
    "explanation": "前立腺癌は血尿で発見されることは少なく、PSA検査や直腸診で発見されることが多いです。他の選択肢は正しいです。"
  },
  {
    "question": "過活動膀胱について正しいのはどれか。",
    "choices": {
      "a": "尿路結石が原因となる。",
      "b": "抗コリン薬が有用である。",
      "c": "PDE5阻害薬が有用である。",
      "d": "骨盤底筋訓練が有用である。",
      "e": "夜間頻尿が診断に必須である。"
    },
    "answer": "b",
    "explanation": "過活動膀胱の治療には抗コリン薬が有効です。他の選択肢は誤りです。"
  },
  {
    "question": "前立腺肥大症の治療として誤っているのはどれか。",
    "choices": {
      "a": "α1遮断薬の投与",
      "b": "尿道カテーテル留置",
      "c": "経尿道的前立腺切除術",
      "d": "LH-RHアゴニストの投与",
      "e": "5α還元酵素阻害薬の投与"
    },
    "answer": "d",
    "explanation": "LH-RHアゴニストは前立腺癌の治療薬であり、前立腺肥大症には使用しません。他の選択肢は前立腺肥大症の治療法として適切です。"
  }
]
